Dalmatia-1.1.2.data/data/CODE_OF_CONDUCT.md
Dalmatia-1.1.2.data/data/CONTRIBUTING.md
Dalmatia-1.1.2.data/data/LICENSE.md
Dalmatia-1.1.2.data/data/README.md
Dalmatia-1.1.2.data/data/requirements.txt
dalmatia/__config__.py
dalmatia/__init__.py
dalmatia/database.py
dalmatia/forger.py
dalmatia/py.typed
dalmatia/reader.py
dalmatia/wrapper.py
dalmatia/tests/__init__.py
dalmatia/tests/py.typed
dalmatia/tests/test_database.py
dalmatia/tests/test_forger.py
dalmatia/tests/test_wrapper.py
Dalmatia-1.1.2.dist-info/LICENSE.md
Dalmatia-1.1.2.dist-info/METADATA
Dalmatia-1.1.2.dist-info/WHEEL
Dalmatia-1.1.2.dist-info/top_level.txt
Dalmatia-1.1.2.dist-info/RECORD
