Metadata-Version: 2.1
Name: Dalmatia
Version: 1.1.2
Summary: CAD addon/plug-in to automize frameworks.
Home-page: https://github.com/IllyrianEngineering/Dalmatia
Author: IllyrianEngineering
Author-email: info@illyrian-engineering.com
License: GNU AFFERO GENERAL PUBLIC LICENSE
Project-URL: Source Code, https://github.com/IllyrianEngineering/Dalmatia
Project-URL: Bug Tracker, https://github.com/IllyrianEngineering/Dalmatia/issues
Project-URL: Documentation, https://wiki.IllyrianEngineering.com/
Project-URL: Funding, https://buymeacoffee.com/illyrius
Requires-Python: >=3.12
License-File: LICENSE.md
Requires-Dist: build
Requires-Dist: setuptools
Requires-Dist: sqlalchemy
